{
  "days": [],
  "profiles": [
    {
      "id": "mnbkdh0bbqg",
      "name": "Alex",
      "food": "횄혘횂째횄혗횂혺횄혗횂짜횄혗횂혰 Vegetarisch",
      "interests": [
        "횄혘횂째횄혗횂혺횄혗횂혥횄혗횂쨘 Pub-Hopping",
        "횄혘횂째횄혗횂혺횄혗횂혴횄혗횂혥횄혘횂짱횄혗횂쨍횄혗횂혧 Shopping",
        "횄혘횂째횄혗횂혺횄혗횂혫횄혗횂쨍 Fotos",
        "횄혘횂째횄혗횂혺횄혗횂혥횄혗횂쩍횄혘횂짱횄혗횂쨍횄혗횂혧 Food"
      ],
      "color": "#2d7a4a"
    },
    {
      "id": "mnbkil6c0ql",
      "name": "Steffiii",
      "food": "횄혘횂째횄혗횂혺횄혗횂짜횄혗횂짤 Fleisch",
      "interests": [
        "횄혘횂째횄혗횂혺횄혗횂혥횄혗횂쨘 Pub-Hopping",
        "횄혘횂째횄혗횂혺횄혗횂혴횄혗횂혥횄혘횂짱횄혗횂쨍횄혗횂혧 Shopping",
        "횄혘횂째횄혗횂혺횄혗횂혣횄혗횂쩔 Parks",
        "횄혘횂째횄혗횂혺횄혗횂혫횄혗횂쨍 Fotos",
        "횄혘횂째횄혗횂혺횄혗횂혥횄혗횂쩍횄혘횂짱횄혗횂쨍횄혗횂혧 Food"
      ],
      "color": "#C8102E"
    }
  ]
}